[{"model": "task_app.Image", "pk": 0, "fields": {"picture": "fountain (1).jpg", "introduction": " ", "category": "fountain"}}, {"model": "task_app.Image", "pk": 1, "fields": {"picture": "fountain (10).jpg", "introduction": " ", "category": "fountain"}}, {"model": "task_app.Image", "pk": 2, "fields": {"picture": "fountain (11).jpg", "introduction": " ", "category": "fountain"}}, {"model": "task_app.Image", "pk": 3, "fields": {"picture": "fountain (12).jpg", "introduction": " ", "category": "fountain"}}, {"model": "task_app.Image", "pk": 4, "fields": {"picture": "fountain (13).jpg", "introduction": " ", "category": "fountain"}}, {"model": "task_app.Image", "pk": 5, "fields": {"picture": "fountain (14).jpg", "introduction": " ", "category": "fountain"}}, {"model": "task_app.Image", "pk": 6, "fields": {"picture": "fountain (15).jpg", "introduction": " ", "category": "fountain"}}, {"model": "task_app.Image", "pk": 7, "fields": {"picture": "fountain (16).jpg", "introduction": " ", "category": "fountain"}}, {"model": "task_app.Image", "pk": 8, "fields": {"picture": "fountain (17).jpg", "introduction": " ", "category": "fountain"}}, {"model": "task_app.Image", "pk": 9, "fields": {"picture": "fountain (18).jpg", "introduction": " ", "category": "fountain"}}, {"model": "task_app.Image", "pk": 10, "fields": {"picture": "fountain (19).jpg", "introduction": " ", "category": "fountain"}}, {"model": "task_app.Image", "pk": 11, "fields": {"picture": "fountain (2).jpg", "introduction": " ", "category": "fountain"}}, {"model": "task_app.Image", "pk": 12, "fields": {"picture": "fountain (20).jpg", "introduction": " ", "category": "fountain"}}, {"model": "task_app.Image", "pk": 13, "fields": {"picture": "fountain (21).jpg", "introduction": " ", "category": "fountain"}}, {"model": "task_app.Image", "pk": 14, "fields": {"picture": "fountain (22).jpg", "introduction": " ", "category": "fountain"}}, {"model": "task_app.Image", "pk": 15, "fields": {"picture": "fountain (23).jpg", "introduction": " ", "category": "fountain"}}, {"model": "task_app.Image", "pk": 16, "fields": {"picture": "fountain (24).jpg", "introduction": " ", "category": "fountain"}}, {"model": "task_app.Image", "pk": 17, "fields": {"picture": "fountain (25).jpg", "introduction": " ", "category": "fountain"}}, {"model": "task_app.Image", "pk": 18, "fields": {"picture": "fountain (26).jpg", "introduction": " ", "category": "fountain"}}, {"model": "task_app.Image", "pk": 19, "fields": {"picture": "fountain (27).jpg", "introduction": " ", "category": "fountain"}}, {"model": "task_app.Image", "pk": 20, "fields": {"picture": "fountain (28).jpg", "introduction": " ", "category": "fountain"}}, {"model": "task_app.Image", "pk": 21, "fields": {"picture": "fountain (29).jpg", "introduction": " ", "category": "fountain"}}, {"model": "task_app.Image", "pk": 22, "fields": {"picture": "fountain (3).jpg", "introduction": " ", "category": "fountain"}}, {"model": "task_app.Image", "pk": 23, "fields": {"picture": "fountain (30).jpg", "introduction": " ", "category": "fountain"}}, {"model": "task_app.Image", "pk": 24, "fields": {"picture": "fountain (31).jpg", "introduction": " ", "category": "fountain"}}, {"model": "task_app.Image", "pk": 25, "fields": {"picture": "fountain (32).jpg", "introduction": " ", "category": "fountain"}}, {"model": "task_app.Image", "pk": 26, "fields": {"picture": "fountain (33).jpg", "introduction": " ", "category": "fountain"}}, {"model": "task_app.Image", "pk": 27, "fields": {"picture": "fountain (34).jpg", "introduction": " ", "category": "fountain"}}, {"model": "task_app.Image", "pk": 28, "fields": {"picture": "fountain (35).jpg", "introduction": " ", "category": "fountain"}}, {"model": "task_app.Image", "pk": 29, "fields": {"picture": "fountain (36).jpg", "introduction": " ", "category": "fountain"}}, {"model": "task_app.Image", "pk": 30, "fields": {"picture": "fountain (37).jpg", "introduction": " ", "category": "fountain"}}, {"model": "task_app.Image", "pk": 31, "fields": {"picture": "fountain (38).jpg", "introduction": " ", "category": "fountain"}}, {"model": "task_app.Image", "pk": 32, "fields": {"picture": "fountain (39).jpg", "introduction": " ", "category": "fountain"}}, {"model": "task_app.Image", "pk": 33, "fields": {"picture": "fountain (4).jpg", "introduction": " ", "category": "fountain"}}, {"model": "task_app.Image", "pk": 34, "fields": {"picture": "fountain (40).jpg", "introduction": " ", "category": "fountain"}}, {"model": "task_app.Image", "pk": 35, "fields": {"picture": "fountain (5).jpg", "introduction": " ", "category": "fountain"}}, {"model": "task_app.Image", "pk": 36, "fields": {"picture": "fountain (6).jpg", "introduction": " ", "category": "fountain"}}, {"model": "task_app.Image", "pk": 37, "fields": {"picture": "fountain (7).jpg", "introduction": " ", "category": "fountain"}}, {"model": "task_app.Image", "pk": 38, "fields": {"picture": "fountain (8).jpg", "introduction": " ", "category": "fountain"}}, {"model": "task_app.Image", "pk": 39, "fields": {"picture": "fountain (9).jpg", "introduction": " ", "category": "fountain"}}, {"model": "task_app.Image", "pk": 40, "fields": {"picture": "furniture (1).jpg", "introduction": " ", "category": "furniture"}}, {"model": "task_app.Image", "pk": 41, "fields": {"picture": "furniture (10).jpg", "introduction": " ", "category": "furniture"}}, {"model": "task_app.Image", "pk": 42, "fields": {"picture": "furniture (11).jpg", "introduction": " ", "category": "furniture"}}, {"model": "task_app.Image", "pk": 43, "fields": {"picture": "furniture (12).jpg", "introduction": " ", "category": "furniture"}}, {"model": "task_app.Image", "pk": 44, "fields": {"picture": "furniture (13).jpg", "introduction": " ", "category": "furniture"}}, {"model": "task_app.Image", "pk": 45, "fields": {"picture": "furniture (14).jpg", "introduction": " ", "category": "furniture"}}, {"model": "task_app.Image", "pk": 46, "fields": {"picture": "furniture (15).jpg", "introduction": " ", "category": "furniture"}}, {"model": "task_app.Image", "pk": 47, "fields": {"picture": "furniture (16).jpg", "introduction": " ", "category": "furniture"}}, {"model": "task_app.Image", "pk": 48, "fields": {"picture": "furniture (17).jpg", "introduction": " ", "category": "furniture"}}, {"model": "task_app.Image", "pk": 49, "fields": {"picture": "furniture (18).jpg", "introduction": " ", "category": "furniture"}}, {"model": "task_app.Image", "pk": 50, "fields": {"picture": "furniture (2).jpg", "introduction": " ", "category": "furniture"}}, {"model": "task_app.Image", "pk": 51, "fields": {"picture": "furniture (3).jpg", "introduction": " ", "category": "furniture"}}, {"model": "task_app.Image", "pk": 52, "fields": {"picture": "furniture (4).jpg", "introduction": " ", "category": "furniture"}}, {"model": "task_app.Image", "pk": 53, "fields": {"picture": "furniture (5).jpg", "introduction": " ", "category": "furniture"}}, {"model": "task_app.Image", "pk": 54, "fields": {"picture": "furniture (6).jpg", "introduction": " ", "category": "furniture"}}, {"model": "task_app.Image", "pk": 55, "fields": {"picture": "furniture (7).jpg", "introduction": " ", "category": "furniture"}}, {"model": "task_app.Image", "pk": 56, "fields": {"picture": "furniture (8).jpg", "introduction": " ", "category": "furniture"}}, {"model": "task_app.Image", "pk": 57, "fields": {"picture": "furniture (9).jpg", "introduction": " ", "category": "furniture"}}, {"model": "task_app.Image", "pk": 58, "fields": {"picture": "ladscap (1).jpg", "introduction": " ", "category": "landscap"}}, {"model": "task_app.Image", "pk": 59, "fields": {"picture": "ladscap (10).jpg", "introduction": " ", "category": "landscap"}}, {"model": "task_app.Image", "pk": 60, "fields": {"picture": "ladscap (11).jpg", "introduction": " ", "category": "landscap"}}, {"model": "task_app.Image", "pk": 61, "fields": {"picture": "ladscap (12).jpg", "introduction": " ", "category": "landscap"}}, {"model": "task_app.Image", "pk": 62, "fields": {"picture": "ladscap (13).jpg", "introduction": " ", "category": "landscap"}}, {"model": "task_app.Image", "pk": 63, "fields": {"picture": "ladscap (14).jpg", "introduction": " ", "category": "landscap"}}, {"model": "task_app.Image", "pk": 64, "fields": {"picture": "ladscap (15).jpg", "introduction": " ", "category": "landscap"}}, {"model": "task_app.Image", "pk": 65, "fields": {"picture": "ladscap (16).jpg", "introduction": " ", "category": "landscap"}}, {"model": "task_app.Image", "pk": 66, "fields": {"picture": "ladscap (17).jpg", "introduction": " ", "category": "landscap"}}, {"model": "task_app.Image", "pk": 67, "fields": {"picture": "ladscap (18).jpg", "introduction": " ", "category": "landscap"}}, {"model": "task_app.Image", "pk": 68, "fields": {"picture": "ladscap (19).jpg", "introduction": " ", "category": "landscap"}}, {"model": "task_app.Image", "pk": 69, "fields": {"picture": "ladscap (2).jpg", "introduction": " ", "category": "landscap"}}, {"model": "task_app.Image", "pk": 70, "fields": {"picture": "ladscap (20).jpg", "introduction": " ", "category": "landscap"}}, {"model": "task_app.Image", "pk": 71, "fields": {"picture": "ladscap (3).jpg", "introduction": " ", "category": "landscap"}}, {"model": "task_app.Image", "pk": 72, "fields": {"picture": "ladscap (4).jpg", "introduction": " ", "category": "landscap"}}, {"model": "task_app.Image", "pk": 73, "fields": {"picture": "ladscap (5).jpg", "introduction": " ", "category": "landscap"}}, {"model": "task_app.Image", "pk": 74, "fields": {"picture": "ladscap (6).jpg", "introduction": " ", "category": "landscap"}}, {"model": "task_app.Image", "pk": 75, "fields": {"picture": "ladscap (7).jpg", "introduction": " ", "category": "landscap"}}, {"model": "task_app.Image", "pk": 76, "fields": {"picture": "ladscap (8).jpg", "introduction": " ", "category": "landscap"}}, {"model": "task_app.Image", "pk": 77, "fields": {"picture": "ladscap (9).jpg", "introduction": " ", "category": "landscap"}}, {"model": "task_app.Image", "pk": 78, "fields": {"picture": "Flower (1).jpg", "introduction": " ", "category": "flowers"}}, {"model": "task_app.Image", "pk": 79, "fields": {"picture": "Flower (12).jpg", "introduction": " ", "category": "flowers"}}, {"model": "task_app.Image", "pk": 80, "fields": {"picture": "Flower (16).jpg", "introduction": " ", "category": "flowers"}}, {"model": "task_app.Image", "pk": 81, "fields": {"picture": "Flower (17).jpg", "introduction": " ", "category": "flowers"}}, {"model": "task_app.Image", "pk": 82, "fields": {"picture": "Flower (20).jpg", "introduction": " ", "category": "flowers"}}, {"model": "task_app.Image", "pk": 83, "fields": {"picture": "Flower (22).jpg", "introduction": " ", "category": "flowers"}}, {"model": "task_app.Image", "pk": 84, "fields": {"picture": "Flower (23).jpg", "introduction": " ", "category": "flowers"}}, {"model": "task_app.Image", "pk": 85, "fields": {"picture": "Flower (24).jpg", "introduction": " ", "category": "flowers"}}, {"model": "task_app.Image", "pk": 86, "fields": {"picture": "Flower (25).jpg", "introduction": " ", "category": "flowers"}}, {"model": "task_app.Image", "pk": 87, "fields": {"picture": "Flower (26).jpg", "introduction": " ", "category": "flowers"}}, {"model": "task_app.Image", "pk": 88, "fields": {"picture": "Flower (27).jpg", "introduction": " ", "category": "flowers"}}, {"model": "task_app.Image", "pk": 89, "fields": {"picture": "Flower (28).jpg", "introduction": " ", "category": "flowers"}}, {"model": "task_app.Image", "pk": 90, "fields": {"picture": "Flower (29).jpg", "introduction": " ", "category": "flowers"}}, {"model": "task_app.Image", "pk": 91, "fields": {"picture": "Flower (30).jpg", "introduction": " ", "category": "flowers"}}, {"model": "task_app.Image", "pk": 92, "fields": {"picture": "Flower (31).jpg", "introduction": " ", "category": "flowers"}}, {"model": "task_app.Image", "pk": 93, "fields": {"picture": "Flower (32).jpg", "introduction": " ", "category": "flowers"}}, {"model": "task_app.Image", "pk": 94, "fields": {"picture": "Flower (33).jpg", "introduction": " ", "category": "flowers"}}, {"model": "task_app.Image", "pk": 95, "fields": {"picture": "Flower (34).jpg", "introduction": " ", "category": "flowers"}}, {"model": "task_app.Image", "pk": 96, "fields": {"picture": "Flower (6).jpg", "introduction": " ", "category": "flowers"}}, {"model": "task_app.Image", "pk": 97, "fields": {"picture": "Flower (9).jpg", "introduction": " ", "category": "flowers"}}, {"model": "task_app.Image", "pk": 98, "fields": {"picture": "TOWNER (1).jpg", "introduction": " ", "category": "towner"}}, {"model": "task_app.Image", "pk": 99, "fields": {"picture": "TOWNER (10).jpg", "introduction": " ", "category": "towner"}}, {"model": "task_app.Image", "pk": 100, "fields": {"picture": "TOWNER (11).jpg", "introduction": " ", "category": "towner"}}, {"model": "task_app.Image", "pk": 101, "fields": {"picture": "TOWNER (12).jpg", "introduction": " ", "category": "towner"}}, {"model": "task_app.Image", "pk": 102, "fields": {"picture": "TOWNER (13).jpg", "introduction": " ", "category": "towner"}}, {"model": "task_app.Image", "pk": 103, "fields": {"picture": "TOWNER (14).jpg", "introduction": " ", "category": "towner"}}, {"model": "task_app.Image", "pk": 104, "fields": {"picture": "TOWNER (15).jpg", "introduction": " ", "category": "towner"}}, {"model": "task_app.Image", "pk": 105, "fields": {"picture": "TOWNER (16).jpg", "introduction": " ", "category": "towner"}}, {"model": "task_app.Image", "pk": 106, "fields": {"picture": "TOWNER (17).jpg", "introduction": " ", "category": "towner"}}, {"model": "task_app.Image", "pk": 107, "fields": {"picture": "TOWNER (18).jpg", "introduction": " ", "category": "towner"}}, {"model": "task_app.Image", "pk": 108, "fields": {"picture": "TOWNER (19).jpg", "introduction": " ", "category": "towner"}}, {"model": "task_app.Image", "pk": 109, "fields": {"picture": "TOWNER (2).jpg", "introduction": " ", "category": "towner"}}, {"model": "task_app.Image", "pk": 110, "fields": {"picture": "TOWNER (20).jpg", "introduction": " ", "category": "towner"}}, {"model": "task_app.Image", "pk": 111, "fields": {"picture": "TOWNER (21).jpg", "introduction": " ", "category": "towner"}}, {"model": "task_app.Image", "pk": 112, "fields": {"picture": "TOWNER (22).jpg", "introduction": " ", "category": "towner"}}, {"model": "task_app.Image", "pk": 113, "fields": {"picture": "TOWNER (23).jpg", "introduction": " ", "category": "towner"}}, {"model": "task_app.Image", "pk": 114, "fields": {"picture": "TOWNER (24).jpg", "introduction": " ", "category": "towner"}}, {"model": "task_app.Image", "pk": 115, "fields": {"picture": "TOWNER (25).jpg", "introduction": " ", "category": "towner"}}, {"model": "task_app.Image", "pk": 116, "fields": {"picture": "TOWNER (26).jpg", "introduction": " ", "category": "towner"}}, {"model": "task_app.Image", "pk": 117, "fields": {"picture": "TOWNER (27).jpg", "introduction": " ", "category": "towner"}}, {"model": "task_app.Image", "pk": 118, "fields": {"picture": "TOWNER (28).jpg", "introduction": " ", "category": "towner"}}, {"model": "task_app.Image", "pk": 119, "fields": {"picture": "TOWNER (29).jpg", "introduction": " ", "category": "towner"}}, {"model": "task_app.Image", "pk": 120, "fields": {"picture": "TOWNER (3).jpg", "introduction": " ", "category": "towner"}}, {"model": "task_app.Image", "pk": 121, "fields": {"picture": "TOWNER (30).jpg", "introduction": " ", "category": "towner"}}, {"model": "task_app.Image", "pk": 122, "fields": {"picture": "TOWNER (31).jpg", "introduction": " ", "category": "towner"}}, {"model": "task_app.Image", "pk": 123, "fields": {"picture": "TOWNER (32).jpg", "introduction": " ", "category": "towner"}}, {"model": "task_app.Image", "pk": 124, "fields": {"picture": "TOWNER (33).jpg", "introduction": " ", "category": "towner"}}, {"model": "task_app.Image", "pk": 125, "fields": {"picture": "TOWNER (34).jpg", "introduction": " ", "category": "towner"}}, {"model": "task_app.Image", "pk": 126, "fields": {"picture": "TOWNER (35).jpg", "introduction": " ", "category": "towner"}}, {"model": "task_app.Image", "pk": 127, "fields": {"picture": "TOWNER (36).jpg", "introduction": " ", "category": "towner"}}, {"model": "task_app.Image", "pk": 128, "fields": {"picture": "TOWNER (37).jpg", "introduction": " ", "category": "towner"}}, {"model": "task_app.Image", "pk": 129, "fields": {"picture": "TOWNER (38).jpg", "introduction": " ", "category": "towner"}}, {"model": "task_app.Image", "pk": 130, "fields": {"picture": "TOWNER (39).jpg", "introduction": " ", "category": "towner"}}, {"model": "task_app.Image", "pk": 131, "fields": {"picture": "TOWNER (4).jpg", "introduction": " ", "category": "towner"}}, {"model": "task_app.Image", "pk": 132, "fields": {"picture": "TOWNER (40).jpg", "introduction": " ", "category": "towner"}}, {"model": "task_app.Image", "pk": 133, "fields": {"picture": "TOWNER (5).jpg", "introduction": " ", "category": "towner"}}, {"model": "task_app.Image", "pk": 134, "fields": {"picture": "TOWNER (6).jpg", "introduction": " ", "category": "towner"}}, {"model": "task_app.Image", "pk": 135, "fields": {"picture": "TOWNER (7).jpg", "introduction": " ", "category": "towner"}}, {"model": "task_app.Image", "pk": 136, "fields": {"picture": "TOWNER (8).jpg", "introduction": " ", "category": "towner"}}, {"model": "task_app.Image", "pk": 137, "fields": {"picture": "TOWNER (9).jpg", "introduction": " ", "category": "towner"}}, {"model": "task_app.Image", "pk": 138, "fields": {"picture": "Tree (1).jpg", "introduction": " ", "category": "tree"}}, {"model": "task_app.Image", "pk": 139, "fields": {"picture": "Tree (10).jpg", "introduction": " ", "category": "tree"}}, {"model": "task_app.Image", "pk": 140, "fields": {"picture": "Tree (11).jpg", "introduction": " ", "category": "tree"}}, {"model": "task_app.Image", "pk": 141, "fields": {"picture": "Tree (12).jpg", "introduction": " ", "category": "tree"}}, {"model": "task_app.Image", "pk": 142, "fields": {"picture": "Tree (13).jpg", "introduction": " ", "category": "tree"}}, {"model": "task_app.Image", "pk": 143, "fields": {"picture": "Tree (14).jpg", "introduction": " ", "category": "tree"}}, {"model": "task_app.Image", "pk": 144, "fields": {"picture": "Tree (15).jpg", "introduction": " ", "category": "tree"}}, {"model": "task_app.Image", "pk": 145, "fields": {"picture": "Tree (16).jpg", "introduction": " ", "category": "tree"}}, {"model": "task_app.Image", "pk": 146, "fields": {"picture": "Tree (17).jpg", "introduction": " ", "category": "tree"}}, {"model": "task_app.Image", "pk": 147, "fields": {"picture": "Tree (18).jpg", "introduction": " ", "category": "tree"}}, {"model": "task_app.Image", "pk": 148, "fields": {"picture": "Tree (19).jpg", "introduction": " ", "category": "tree"}}, {"model": "task_app.Image", "pk": 149, "fields": {"picture": "Tree (2).jpg", "introduction": " ", "category": "tree"}}, {"model": "task_app.Image", "pk": 150, "fields": {"picture": "Tree (20).jpg", "introduction": " ", "category": "tree"}}, {"model": "task_app.Image", "pk": 151, "fields": {"picture": "Tree (21).jpg", "introduction": " ", "category": "tree"}}, {"model": "task_app.Image", "pk": 152, "fields": {"picture": "Tree (22).jpg", "introduction": " ", "category": "tree"}}, {"model": "task_app.Image", "pk": 153, "fields": {"picture": "Tree (23).jpg", "introduction": " ", "category": "tree"}}, {"model": "task_app.Image", "pk": 154, "fields": {"picture": "Tree (3).jpg", "introduction": " ", "category": "tree"}}, {"model": "task_app.Image", "pk": 155, "fields": {"picture": "Tree (4).jpg", "introduction": " ", "category": "tree"}}, {"model": "task_app.Image", "pk": 156, "fields": {"picture": "Tree (5).jpg", "introduction": " ", "category": "tree"}}, {"model": "task_app.Image", "pk": 157, "fields": {"picture": "Tree (6).jpg", "introduction": " ", "category": "tree"}}, {"model": "task_app.Image", "pk": 158, "fields": {"picture": "Tree (7).jpg", "introduction": " ", "category": "tree"}}, {"model": "task_app.Image", "pk": 159, "fields": {"picture": "Tree (8).jpg", "introduction": " ", "category": "tree"}}, {"model": "task_app.Image", "pk": 160, "fields": {"picture": "Tree (9).jpg", "introduction": " ", "category": "tree"}}, {"model": "task_app.Image", "pk": 161, "fields": {"picture": "kettle (1).jpg", "introduction": " ", "category": "kettle"}}, {"model": "task_app.Image", "pk": 162, "fields": {"picture": "kettle (11).jpg", "introduction": " ", "category": "kettle"}}, {"model": "task_app.Image", "pk": 163, "fields": {"picture": "kettle (14).jpg", "introduction": " ", "category": "kettle"}}, {"model": "task_app.Image", "pk": 164, "fields": {"picture": "kettle (15).jpg", "introduction": " ", "category": "kettle"}}, {"model": "task_app.Image", "pk": 165, "fields": {"picture": "kettle (16).jpg", "introduction": " ", "category": "kettle"}}, {"model": "task_app.Image", "pk": 166, "fields": {"picture": "kettle (2).jpg", "introduction": " ", "category": "kettle"}}, {"model": "task_app.Image", "pk": 167, "fields": {"picture": "kettle (21).jpg", "introduction": " ", "category": "kettle"}}, {"model": "task_app.Image", "pk": 168, "fields": {"picture": "kettle (22).jpg", "introduction": " ", "category": "kettle"}}, {"model": "task_app.Image", "pk": 169, "fields": {"picture": "kettle (23).jpg", "introduction": " ", "category": "kettle"}}, {"model": "task_app.Image", "pk": 170, "fields": {"picture": "kettle (24).jpg", "introduction": " ", "category": "kettle"}}, {"model": "task_app.Image", "pk": 171, "fields": {"picture": "kettle (25).jpg", "introduction": " ", "category": "kettle"}}, {"model": "task_app.Image", "pk": 172, "fields": {"picture": "kettle (26).jpg", "introduction": " ", "category": "kettle"}}, {"model": "task_app.Image", "pk": 173, "fields": {"picture": "kettle (27).jpg", "introduction": " ", "category": "kettle"}}, {"model": "task_app.Image", "pk": 174, "fields": {"picture": "kettle (28).jpg", "introduction": " ", "category": "kettle"}}, {"model": "task_app.Image", "pk": 175, "fields": {"picture": "kettle (29).jpg", "introduction": " ", "category": "kettle"}}, {"model": "task_app.Image", "pk": 176, "fields": {"picture": "kettle (3).jpg", "introduction": " ", "category": "kettle"}}, {"model": "task_app.Image", "pk": 177, "fields": {"picture": "kettle (30).jpg", "introduction": " ", "category": "kettle"}}, {"model": "task_app.Image", "pk": 178, "fields": {"picture": "kettle (31).jpg", "introduction": " ", "category": "kettle"}}, {"model": "task_app.Image", "pk": 179, "fields": {"picture": "kettle (7).jpg", "introduction": " ", "category": "kettle"}}, {"model": "task_app.Image", "pk": 180, "fields": {"picture": "kettle (8).jpg", "introduction": " ", "category": "kettle"}}, {"model": "task_app.Image", "pk": 181, "fields": {"picture": "Spoon (1).jpg", "introduction": " ", "category": "spoon"}}, {"model": "task_app.Image", "pk": 182, "fields": {"picture": "Spoon (10).jpg", "introduction": " ", "category": "spoon"}}, {"model": "task_app.Image", "pk": 183, "fields": {"picture": "Spoon (11).jpg", "introduction": " ", "category": "spoon"}}, {"model": "task_app.Image", "pk": 184, "fields": {"picture": "Spoon (12).jpg", "introduction": " ", "category": "spoon"}}, {"model": "task_app.Image", "pk": 185, "fields": {"picture": "Spoon (13).jpg", "introduction": " ", "category": "spoon"}}, {"model": "task_app.Image", "pk": 186, "fields": {"picture": "Spoon (14).jpg", "introduction": " ", "category": "spoon"}}, {"model": "task_app.Image", "pk": 187, "fields": {"picture": "Spoon (15).jpg", "introduction": " ", "category": "spoon"}}, {"model": "task_app.Image", "pk": 188, "fields": {"picture": "Spoon (16).jpg", "introduction": " ", "category": "spoon"}}, {"model": "task_app.Image", "pk": 189, "fields": {"picture": "Spoon (17).jpg", "introduction": " ", "category": "spoon"}}, {"model": "task_app.Image", "pk": 190, "fields": {"picture": "Spoon (18).jpg", "introduction": " ", "category": "spoon"}}, {"model": "task_app.Image", "pk": 191, "fields": {"picture": "Spoon (19).jpg", "introduction": " ", "category": "spoon"}}, {"model": "task_app.Image", "pk": 192, "fields": {"picture": "Spoon (2).jpg", "introduction": " ", "category": "spoon"}}, {"model": "task_app.Image", "pk": 193, "fields": {"picture": "Spoon (20).jpg", "introduction": " ", "category": "spoon"}}, {"model": "task_app.Image", "pk": 194, "fields": {"picture": "Spoon (3).jpg", "introduction": " ", "category": "spoon"}}, {"model": "task_app.Image", "pk": 195, "fields": {"picture": "Spoon (4).jpg", "introduction": " ", "category": "spoon"}}, {"model": "task_app.Image", "pk": 196, "fields": {"picture": "Spoon (5).jpg", "introduction": " ", "category": "spoon"}}, {"model": "task_app.Image", "pk": 197, "fields": {"picture": "Spoon (6).jpg", "introduction": " ", "category": "spoon"}}, {"model": "task_app.Image", "pk": 198, "fields": {"picture": "Spoon (7).jpg", "introduction": " ", "category": "spoon"}}, {"model": "task_app.Image", "pk": 199, "fields": {"picture": "Spoon (8).jpg", "introduction": " ", "category": "spoon"}}, {"model": "task_app.Image", "pk": 200, "fields": {"picture": "Spoon (9).jpg", "introduction": " ", "category": "spoon"}}, {"model": "task_app.Image", "pk": 201, "fields": {"picture": "tools (1).jpg", "introduction": " ", "category": "tools"}}, {"model": "task_app.Image", "pk": 202, "fields": {"picture": "tools (10).jpg", "introduction": " ", "category": "tools"}}, {"model": "task_app.Image", "pk": 203, "fields": {"picture": "tools (11).jpg", "introduction": " ", "category": "tools"}}, {"model": "task_app.Image", "pk": 204, "fields": {"picture": "tools (12).jpg", "introduction": " ", "category": "tools"}}, {"model": "task_app.Image", "pk": 205, "fields": {"picture": "tools (13).jpg", "introduction": " ", "category": "tools"}}, {"model": "task_app.Image", "pk": 206, "fields": {"picture": "tools (14).jpg", "introduction": " ", "category": "tools"}}, {"model": "task_app.Image", "pk": 207, "fields": {"picture": "tools (15).jpg", "introduction": " ", "category": "tools"}}, {"model": "task_app.Image", "pk": 208, "fields": {"picture": "tools (16).jpg", "introduction": " ", "category": "tools"}}, {"model": "task_app.Image", "pk": 209, "fields": {"picture": "tools (17).jpg", "introduction": " ", "category": "tools"}}, {"model": "task_app.Image", "pk": 210, "fields": {"picture": "tools (18).jpg", "introduction": " ", "category": "tools"}}, {"model": "task_app.Image", "pk": 211, "fields": {"picture": "tools (2).jpg", "introduction": " ", "category": "tools"}}, {"model": "task_app.Image", "pk": 212, "fields": {"picture": "tools (3).jpg", "introduction": " ", "category": "tools"}}, {"model": "task_app.Image", "pk": 213, "fields": {"picture": "tools (4).jpg", "introduction": " ", "category": "tools"}}, {"model": "task_app.Image", "pk": 214, "fields": {"picture": "tools (5).jpg", "introduction": " ", "category": "tools"}}, {"model": "task_app.Image", "pk": 215, "fields": {"picture": "tools (6).jpg", "introduction": " ", "category": "tools"}}, {"model": "task_app.Image", "pk": 216, "fields": {"picture": "tools (7).jpg", "introduction": " ", "category": "tools"}}, {"model": "task_app.Image", "pk": 217, "fields": {"picture": "tools (8).jpg", "introduction": " ", "category": "tools"}}, {"model": "task_app.Image", "pk": 218, "fields": {"picture": "tools (9).jpg", "introduction": " ", "category": "tools"}}]